jentic/apitools/openapi/parser/backends/base.py
jentic/apitools/openapi/parser/backends/datamodel_low.py
jentic/apitools/openapi/parser/backends/py.typed
jentic/apitools/openapi/parser/backends/pyyaml.py
jentic/apitools/openapi/parser/backends/ruamel_ast.py
jentic/apitools/openapi/parser/backends/ruamel_roundtrip.py
jentic/apitools/openapi/parser/backends/ruamel_safe.py
jentic/apitools/openapi/parser/core/__init__.py
jentic/apitools/openapi/parser/core/exceptions.py
jentic/apitools/openapi/parser/core/loader.py
jentic/apitools/openapi/parser/core/openapi_parser.py
jentic/apitools/openapi/parser/core/py.typed
jentic/apitools/openapi/parser/core/serialization.py
jentic_openapi_parser-1.0.0a34.dist-info/licenses/LICENSE
jentic_openapi_parser-1.0.0a34.dist-info/licenses/NOTICE
jentic_openapi_parser-1.0.0a34.dist-info/WHEEL
jentic_openapi_parser-1.0.0a34.dist-info/entry_points.txt
jentic_openapi_parser-1.0.0a34.dist-info/METADATA
jentic_openapi_parser-1.0.0a34.dist-info/RECORD
