Metadata-Version: 2.4
Name: jentic-openapi-parser
Version: 1.0.0a34
Summary: Jentic OpenAPI Parser
Author: Jentic
Author-email: Jentic <hello@jentic.com>
License-Expression: Apache-2.0
License-File: LICENSE
License-File: NOTICE
Requires-Dist: attrs~=25.4.0
Requires-Dist: jentic-openapi-common~=1.0.0a34
Requires-Dist: jentic-openapi-datamodels~=1.0.0a34
Requires-Dist: pyyaml~=6.0.3
Requires-Dist: requests~=2.32.5
Requires-Dist: ruamel-yaml~=0.18.15
Requires-Python: >=3.11
Project-URL: Homepage, https://github.com/jentic/jentic-openapi-tools
